turbo_broccoli/__init__.py
turbo_broccoli/context.py
turbo_broccoli/exceptions.py
turbo_broccoli/guard.py
turbo_broccoli/native.py
turbo_broccoli/parallel.py
turbo_broccoli/turbo_broccoli.py
turbo_broccoli/user.py
turbo_broccoli/custom/__init__.py
turbo_broccoli/custom/bokeh.py
turbo_broccoli/custom/bytes.py
turbo_broccoli/custom/collections.py
turbo_broccoli/custom/dataclass.py
turbo_broccoli/custom/datetime.py
turbo_broccoli/custom/dct.py
turbo_broccoli/custom/embedded.py
turbo_broccoli/custom/external.py
turbo_broccoli/custom/generic.py
turbo_broccoli/custom/keras.py
turbo_broccoli/custom/networkx.py
turbo_broccoli/custom/numpy.py
turbo_broccoli/custom/pandas.py
turbo_broccoli/custom/pathlib.py
turbo_broccoli/custom/pytorch.py
turbo_broccoli/custom/scipy.py
turbo_broccoli/custom/secret.py
turbo_broccoli/custom/sklearn.py
turbo_broccoli/custom/tensorflow.py
turbo_broccoli/custom/uuid.py
turbo_broccoli-4.12.2.dist-info/LICENSE
turbo_broccoli-4.12.2.dist-info/METADATA
turbo_broccoli-4.12.2.dist-info/WHEEL
turbo_broccoli-4.12.2.dist-info/top_level.txt
turbo_broccoli-4.12.2.dist-info/RECORD
