Metadata-Version: 2.1
Name: turbo_broccoli
Version: 4.12.2
Summary: JSON (de)serialization extensions
Home-page: https://github.com/altaris/turbo-broccoli
Author: Cédric Ho Thanh
Author-email: altaris@users.noreply.github.com
Project-URL: Issues, https://github.com/altaris/turbo-broccoli/issues
Platform: any
Classifier: License :: OSI Approved :: MIT License
Classifier: Operating System :: OS Independent
Classifier: Programming Language :: Python :: 3
Classifier: Programming Language :: Python :: 3.10
Classifier: Programming Language :: Python :: 3.11
Requires-Python: >=3.10
License-File: LICENSE
